telnetserver/__init__.py
telnetserver/telnetserver.py
telnetserver-0.6.dist-info/LICENSE.txt
telnetserver-0.6.dist-info/METADATA
telnetserver-0.6.dist-info/WHEEL
telnetserver-0.6.dist-info/top_level.txt
telnetserver-0.6.dist-info/RECORD
