Metadata-Version: 2.1
Name: telnetserver
Version: 0.6
Summary: Really simple and easy to use telnet server for small projects.
Author-email: "Óliver L. Sanz" <oliverlsanz@gmail.com>
License: MIT License
Project-URL: Homepage, https://github.com/OliverLSanz/python-telnetserver
Keywords: telnet,server
Classifier: License :: OSI Approved :: MIT License
Classifier: Programming Language :: Python
Classifier: Programming Language :: Python :: 3
Requires-Python: >=3.8
License-File: LICENSE.txt
Provides-Extra: dev
